README.md
setup.py
certifier/__init__.py
certifier/core.py
certifier.egg-info/PKG-INFO
certifier.egg-info/SOURCES.txt
certifier.egg-info/dependency_links.txt
certifier.egg-info/top_level.txt