Metadata-Version: 2.1
Name: certifier
Version: 0.2.1
Summary: Get all the information you need about your SSL certificates.
Home-page: https://github.com/barnumbirr/certifier
Author: Martin Simon
Author-email: me@martinsimon.me
License: Apache v2.0 License
Project-URL: Buy me a coffee, https://github.com/barnumbirr/certifier#buy-me-a-coffee
Project-URL: Bug Reports, https://github.com/barnumbirr/certifier/issues
Keywords: TLS,certificate,SSL
Platform: UNKNOWN
Classifier: License :: OSI Approved :: Apache Software License
Classifier: Development Status :: 5 - Production/Stable
Classifier: Intended Audience :: Developers
Classifier: Programming Language :: Python
Classifier: Programming Language :: Python :: 2.7
Classifier: Programming Language :: Python :: 3.6
Classifier: Topic :: Software Development :: Libraries :: Python Modules
